ldt_people_client_async_staging/__init__.py
ldt_people_client_async_staging/api_client.py
ldt_people_client_async_staging/api_response.py
ldt_people_client_async_staging/configuration.py
ldt_people_client_async_staging/exceptions.py
ldt_people_client_async_staging/py.typed
ldt_people_client_async_staging/rest.py
ldt_people_client_async_staging/api/__init__.py
ldt_people_client_async_staging/api/admin_find_samples_api.py
ldt_people_client_async_staging/api/default_api.py
ldt_people_client_async_staging/api/search_api.py
ldt_people_client_async_staging/api/verification_api.py
ldt_people_client_async_staging/models/__init__.py
ldt_people_client_async_staging/models/agg_request.py
ldt_people_client_async_staging/models/agg_response.py
ldt_people_client_async_staging/models/agg_response_buckets_inner.py
ldt_people_client_async_staging/models/company.py
ldt_people_client_async_staging/models/delete_success_message.py
ldt_people_client_async_staging/models/download_persons_data200_response.py
ldt_people_client_async_staging/models/download_persons_data_request.py
ldt_people_client_async_staging/models/f_company.py
ldt_people_client_async_staging/models/filter_group.py
ldt_people_client_async_staging/models/filter_group_filters_inner.py
ldt_people_client_async_staging/models/find200_response.py
ldt_people_client_async_staging/models/find200_response_matches_inner.py
ldt_people_client_async_staging/models/find200_response_matches_inner_people_inner.py
ldt_people_client_async_staging/models/find_company200_response.py
ldt_people_client_async_staging/models/find_company_request.py
ldt_people_client_async_staging/models/find_preview200_response.py
ldt_people_client_async_staging/models/find_preview200_response_matches_inner.py
ldt_people_client_async_staging/models/find_preview200_response_matches_inner_people_inner.py
ldt_people_client_async_staging/models/find_preview_request.py
ldt_people_client_async_staging/models/find_preview_request_matches_inner.py
ldt_people_client_async_staging-1.0.129.dist-info/METADATA
ldt_people_client_async_staging-1.0.129.dist-info/WHEEL
ldt_people_client_async_staging-1.0.129.dist-info/top_level.txt
ldt_people_client_async_staging-1.0.129.dist-info/RECORD
