Metadata-Version: 2.1
Name: ldt-people-client-async-staging
Version: 1.0.129
Summary: Live Data People API
Home-page: 
Author: Live Data Technologies
Author-email: support@livedatatechnologies.com
License: Attribution-NoDerivs
Keywords: OpenAPI,OpenAPI-Generator,Live Data People API
Requires-Dist: urllib3<3.0.0,>=2.1.0
Requires-Dist: python-dateutil>=2.8.2
Requires-Dist: aiohttp>=3.8.4
Requires-Dist: aiohttp-retry>=2.8.3
Requires-Dist: pydantic>=2
Requires-Dist: typing-extensions>=4.7.1
